odoo8_addon_l10n_br_delivery-8.0.1.0.0.99.dev5-py2.7-nspkg.pth
odoo8_addon_l10n_br_delivery-8.0.1.0.0.99.dev5.dist-info/METADATA
odoo8_addon_l10n_br_delivery-8.0.1.0.0.99.dev5.dist-info/RECORD
odoo8_addon_l10n_br_delivery-8.0.1.0.0.99.dev5.dist-info/WHEEL
odoo8_addon_l10n_br_delivery-8.0.1.0.0.99.dev5.dist-info/namespace_packages.txt
odoo8_addon_l10n_br_delivery-8.0.1.0.0.99.dev5.dist-info/top_level.txt
odoo_addons/l10n_br_delivery/README.rst
odoo_addons/l10n_br_delivery/__init__.py
odoo_addons/l10n_br_delivery/__openerp__.py
odoo_addons/l10n_br_delivery/i18n/pt_BR.po
odoo_addons/l10n_br_delivery/models/__init__.py
odoo_addons/l10n_br_delivery/models/account_invoice.py
odoo_addons/l10n_br_delivery/models/delivery.py
odoo_addons/l10n_br_delivery/models/l10n_br_delivery.py
odoo_addons/l10n_br_delivery/models/sale.py
odoo_addons/l10n_br_delivery/models/stock.py
odoo_addons/l10n_br_delivery/security/ir.model.access.csv
odoo_addons/l10n_br_delivery/static/description/icon.png
odoo_addons/l10n_br_delivery/views/account_invoice_view.xml
odoo_addons/l10n_br_delivery/views/delivery_view.xml
odoo_addons/l10n_br_delivery/views/l10n_br_delivery_view.xml
odoo_addons/l10n_br_delivery/views/stock_view.xml
